audit_logging/__init__.py
audit_logging/apps.py
audit_logging/constants.py
audit_logging/formatters.py
audit_logging/handlers.py
audit_logging/logger_levels.py
audit_logging/middleware.py
audit_logging/protocols.py
audit_logging/settings.py
audit_logging/signals.py
audit_logging/utils.py
audit_logging-0.0.2.dist-info/METADATA
audit_logging-0.0.2.dist-info/WHEEL
audit_logging-0.0.2.dist-info/licenses/LICENSE
audit_logging-0.0.2.dist-info/RECORD
