Metadata-Version: 2.4
Name: audit-logging
Version: 0.0.2
Summary: A Django package for easy CRUD operation logging and container logs
Project-URL: Homepage, https://github.com/shree256/audit-logging
Project-URL: Repository, https://github.com/shree256/audit-logging
Project-URL: Documentation, https://github.com/shree256/audit-logging
Author-email: Shreeshan <shreeshan256@gmail.com>
License: MIT
License-File: LICENSE
Keywords: audit,django,logging,utilities
Classifier: Environment :: Plugins
Classifier: Framework :: Django
Classifier: Framework :: Django :: 4.2
Classifier: Framework :: Django :: 5.0
Classifier: Intended Audience :: Developers
Classifier: License :: OSI Approved :: MIT License
Classifier: Operating System :: OS Independent
Classifier: Programming Language :: Python :: 3
Classifier: Programming Language :: Python :: 3 :: Only
Classifier: Programming Language :: Python :: 3.8
Classifier: Programming Language :: Python :: 3.9
Classifier: Programming Language :: Python :: 3.10
Classifier: Programming Language :: Python :: 3.11
Classifier: Programming Language :: Python :: 3.12
Classifier: Topic :: Software Development :: Libraries :: Python Modules
Requires-Python: >=3.8
Requires-Dist: django<6.0,>=4.2
Provides-Extra: dev
Requires-Dist: pre-commit>=3.5; (python_version >= '3.9') and extra == 'dev'
Requires-Dist: pre-commit~=3.5; (python_version < '3.9') and extra == 'dev'
Requires-Dist: ruff>=0.1.11; extra == 'dev'
